bottle_tools/__init__.py
bottle_tools/__main__.py
bottle_tools/cli.py
bottle_tools/plugins.py
bottle_tools-2019.4.17.dist-info/LICENSE
bottle_tools-2019.4.17.dist-info/METADATA
bottle_tools-2019.4.17.dist-info/WHEEL
bottle_tools-2019.4.17.dist-info/top_level.txt
bottle_tools-2019.4.17.dist-info/RECORD
