Metadata-Version: 2.1
Name: bottle-tools
Version: 2019.4.17
Summary: UNKNOWN
Home-page: UNKNOWN
Author: Arjoonn Sharma
License: UNKNOWN
Project-URL: Source, https://github.com/thesage21/bottle_tools
Platform: UNKNOWN
Requires-Python: >=3.6
Requires-Dist: bottle
